niconico_dl/__init__.py
niconico_dl/__main__.py
niconico_dl/async_video_manager.py
niconico_dl/templates.py
niconico_dl/video_manager.py
niconico_dl-2.2.8.dist-info/LICENSE
niconico_dl-2.2.8.dist-info/METADATA
niconico_dl-2.2.8.dist-info/WHEEL
niconico_dl-2.2.8.dist-info/entry_points.txt
niconico_dl-2.2.8.dist-info/top_level.txt
niconico_dl-2.2.8.dist-info/RECORD
