Metadata-Version: 2.1
Name: niconico-dl
Version: 2.2.8
Summary: ニコニコ動画ダウンローダー NicoNico Video Downloader
Home-page: https://tasuren.github.io/niconico_dl/
Author: tasuren
Author-email: tasuren5@gmail.com
License: MIT
Keywords: niconico video download
Platform: UNKNOWN
Classifier: Programming Language :: Python :: 3.6
Classifier: Programming Language :: Python :: 3.7
Classifier: Programming Language :: Python :: 3.8
Classifier: Programming Language :: Python :: 3.9
License-File: LICENSE
Requires-Dist: aiofiles
Requires-Dist: aiohttp
Requires-Dist: requests
Requires-Dist: bs4
